blogger_cli/__init__.py
blogger_cli/blog_manager/__init__.py
blogger_cli/blog_manager/add_post.py
blogger_cli/blog_manager/add_post_meta.py
blogger_cli/cli.py
blogger_cli/cli_utils/__init__.py
blogger_cli/cli_utils/installation.py
blogger_cli/cli_utils/json_writer.py
blogger_cli/commands/__init__.py
blogger_cli/commands/cmd_addblog.py
blogger_cli/commands/cmd_addfeed.py
blogger_cli/commands/cmd_config.py
blogger_cli/commands/cmd_convert.py
blogger_cli/commands/cmd_export.py
blogger_cli/commands/cmd_info.py
blogger_cli/commands/cmd_rmblog.py
blogger_cli/commands/cmd_serve.py
blogger_cli/commands/cmd_setdefault.py
blogger_cli/commands/cmd_setupblog.py
blogger_cli/commands/cmd_spellcheck.py
blogger_cli/commands/cmd_uninstall.py
blogger_cli/commands/cmd_update.py
blogger_cli/commands/convert_utils/__init__.py
blogger_cli/commands/convert_utils/classifier.py
blogger_cli/commands/export_utils/__init__.py
blogger_cli/commands/export_utils/copier.py
blogger_cli/commands/feed_utils/feed.py
blogger_cli/commands/feed_utils/feed_template.py
blogger_cli/commands/feed_utils/feedprocessor.py
blogger_cli/commands/serve_utils/__init__.py
blogger_cli/converter/__init__.py
blogger_cli/converter/extractor.py
blogger_cli/converter/ipynb_to_html.py
blogger_cli/converter/md_to_html.py
blogger_cli/resources/__init__.py
blogger_cli/resources/blog_index.html
blogger_cli/resources/blog_layout/_blogger_templates/css.html
blogger_cli/resources/blog_layout/_blogger_templates/dark_theme.html
blogger_cli/resources/blog_layout/_blogger_templates/disqus.html
blogger_cli/resources/blog_layout/_blogger_templates/google_analytics.html
blogger_cli/resources/blog_layout/_blogger_templates/js.html
blogger_cli/resources/blog_layout/_blogger_templates/layout.html
blogger_cli/resources/blog_layout/_blogger_templates/li_tag.html
blogger_cli/resources/blog_layout/_blogger_templates/light_theme.html
blogger_cli/resources/blog_layout/_blogger_templates/mathjax.html
blogger_cli-1.2.4.dist-info/entry_points.txt
blogger_cli-1.2.4.dist-info/LICENSE
blogger_cli-1.2.4.dist-info/WHEEL
blogger_cli-1.2.4.dist-info/METADATA
blogger_cli-1.2.4.dist-info/RECORD
