Metadata-Version: 2.1
Name: blogger-cli
Version: 1.2.4
Summary: Blogger cli is a CLI tool to convert ipynb, md, html file to responsive html files.
Home-page: https://github.com/hemanta212/blogger-cli
License: MIT
Keywords: jupyter notebook,github pages,blogger
Author: hemanta212
Author-email: sharmahemanta.212@gmail.com
Requires-Python: >=3.6,<4.0
Classifier: License :: OSI Approved :: MIT License
Classifier: Programming Language :: Python :: 3
Classifier: Programming Language :: Python :: 3.10
Classifier: Programming Language :: Python :: 3.6
Classifier: Programming Language :: Python :: 3.7
Classifier: Programming Language :: Python :: 3.8
Classifier: Programming Language :: Python :: 3.9
Requires-Dist: bs4 (>=0.0.1,<0.0.2)
Requires-Dist: click (>=7.0,<8.0)
Requires-Dist: colorama (>=0.4.1,<0.5.0)
Requires-Dist: feedgen (>=0.9.0,<0.10.0)
Requires-Dist: markdown (>=3.1,<4.0)
Requires-Dist: misspellings (>=1.5,<2.0)
Requires-Dist: nbconvert (>=5.5,<6.0)
Requires-Dist: pyspellchecker (>=0.5.0,<0.6.0)
Requires-Dist: selectolax (>=0.2.1,<0.3.0)
Project-URL: Documentation, https://hemanta212.github.io/blogger-cli
Project-URL: Repository, https://github.com/hemanta212/blogger-cli
